odoo10_addon_project_wbs-10.0.1.1.0.99.dev5-nspkg.pth
odoo/addons/project_wbs/README.rst
odoo/addons/project_wbs/__init__.py
odoo/addons/project_wbs/__manifest__.py
odoo/addons/project_wbs/hooks.py
odoo/addons/project_wbs/i18n/project_wbs.pot
odoo/addons/project_wbs/models/__init__.py
odoo/addons/project_wbs/models/account_analytic_account.py
odoo/addons/project_wbs/models/project_project.py
odoo/addons/project_wbs/static/description/icon.png
odoo/addons/project_wbs/tests/__init__.py
odoo/addons/project_wbs/tests/test_project_wbs.py
odoo/addons/project_wbs/view/account_analytic_account_view.xml
odoo/addons/project_wbs/view/project_project_view.xml
odoo10_addon_project_wbs-10.0.1.1.0.99.dev5.dist-info/METADATA
odoo10_addon_project_wbs-10.0.1.1.0.99.dev5.dist-info/WHEEL
odoo10_addon_project_wbs-10.0.1.1.0.99.dev5.dist-info/namespace_packages.txt
odoo10_addon_project_wbs-10.0.1.1.0.99.dev5.dist-info/top_level.txt
odoo10_addon_project_wbs-10.0.1.1.0.99.dev5.dist-info/RECORD
