Metadata-Version: 2.1
Name: odoo10-addon-project-wbs
Version: 10.0.1.1.0.99.dev5
Summary: Project Work Breakdown Structure
Home-page: https://www.github.com/OCA/project
Author: Matmoz d.o.o., Luxim d.o.o., Deneroteam, Eficent, Odoo Community Association (OCA)
Author-email: support@odoo-community.org
License: AGPL-3
Platform: UNKNOWN
Classifier: Programming Language :: Python
Classifier: Framework :: Odoo
Classifier: License :: OSI Approved :: GNU Affero General Public License v3
Requires-Python: ~=2.7
Requires-Dist: odoo10-addon-account-analytic-parent
Requires-Dist: odoo10-addon-account-analytic-sequence
Requires-Dist: odoo (<10.1dev,>=10.0)
